spamosaic/MNN.py
spamosaic/__init__.py
spamosaic/build_graph.py
spamosaic/framework.py
spamosaic/loss.py
spamosaic/preprocessing.py
spamosaic/train_utils.py
spamosaic/utils.py
spamosaic/architectures/gat.py
spamosaic/architectures/hg_lgcn.py
spamosaic/architectures/hgt.py
spamosaic/architectures/wlgcn.py
spamosaic/configs/wlgcn.yaml
spamosaic/configs/.ipynb_checkpoints/wlgcn-checkpoint.yaml
spamosaic-1.0.3.dist-info/LICENSE
spamosaic-1.0.3.dist-info/METADATA
spamosaic-1.0.3.dist-info/WHEEL
spamosaic-1.0.3.dist-info/top_level.txt
spamosaic-1.0.3.dist-info/RECORD
