Metadata-Version: 2.1
Name: spamosaic
Version: 1.0.3
Summary: SpaMosaic: Mosaic Integration of Spatial Multi-omics
Author-email: Jinmiao Lab <3200376951@qq.com>
License: MIT
Requires-Python: >=3.8
License-File: LICENSE
Requires-Dist: anndata>=0.9.2
Requires-Dist: scanpy>=1.9.6
Requires-Dist: pandas>=1.5.3
Requires-Dist: h5py>=3.10.0
Requires-Dist: numpy>=1.22.4
Requires-Dist: scikit-learn>=1.3.2
Requires-Dist: seaborn>=0.12.2
Requires-Dist: tqdm>=4.66.1
Requires-Dist: matplotlib>=3.7.4
Requires-Dist: hnswlib
Requires-Dist: annoy
Requires-Dist: PyYAML>=6.0.1
Requires-Dist: networkx>=3.1
Requires-Dist: scipy>=1.10.1
